{
 "updated_at": "2026-06-23T02:07:49+08:00",
 "trading_date": "20260622",
 "quarter_end": true,
 "universe": 120,
 "shown": 40,
 "market_split": {
  "twse": 37,
  "tpex": 3
 },
 "sources": {
  "twse": true,
  "tpex": true,
  "broker": false,
  "fundamentals": true,
  "overseas": true,
  "news": true,
  "history": true,
  "tdcc": true,
  "futures": true
 },
 "topic_momentum": {
  "記憶體": 27.26,
  "AI伺服器": 8.8,
  "晶圓代工": 10.39,
  "IC設計": 5.59,
  "CoWoS先進封裝": 7.3,
  "矽光子CPO": 5.55,
  "散熱": 16.63,
  "機器人": 10.52,
  "重電綠能": 15.18,
  "軍工航太": -5.2,
  "PCB": 21.58,
  "矽智財IP": 2.39,
  "被動元件": 24.45,
  "蘋果供應鏈": 2.58,
  "低軌衛星": -6.45,
  "航運": -3.74,
  "金融": 0.65,
  "網通": 3.61,
  "綠能": -0.71,
  "塑化": -9.04,
  "鋼鐵": -8.59,
  "生技新藥": 9.23
 },
 "topic_heat": {
  "記憶體": 2,
  "AI伺服器": 19,
  "晶圓代工": 0,
  "IC設計": 0,
  "CoWoS先進封裝": 3,
  "矽光子CPO": 2,
  "散熱": 0,
  "機器人": 3,
  "重電綠能": 0,
  "軍工航太": 0,
  "PCB": 0,
  "矽智財IP": 0,
  "被動元件": 4,
  "蘋果供應鏈": 1,
  "低軌衛星": 10,
  "航運": 2,
  "營建資產": 0,
  "金融": 0,
  "網通": 0,
  "綠能": 0,
  "塑化": 0,
  "鋼鐵": 2,
  "生技新藥": 0
 },
 "yahoo_ok": 290,
 "market_pulse": {
  "advancers": 1184,
  "decliners": 863,
  "unchanged": 192,
  "breadth_pct": 57.8,
  "inst_foreign": 684.6,
  "inst_trust": -105.2,
  "inst_dealer": 121.0,
  "inst_total": 700.4,
  "margin_chg_lots": 48970.0,
  "margin_up_count": 859,
  "hot_topics": [
   {
    "name": "AI伺服器",
    "heat": 19,
    "mom": 8.8
   },
   {
    "name": "記憶體",
    "heat": 2,
    "mom": 27.3
   },
   {
    "name": "被動元件",
    "heat": 4,
    "mom": 24.4
   }
  ],
  "mood": "neutral",
  "mood_text": "中性"
 }
}