{
 "updated_at": "2026-07-03T19:46:31+08:00",
 "trading_date": "20260703",
 "quarter_end": false,
 "universe": 120,
 "shown": 40,
 "market_split": {
  "twse": 38,
  "tpex": 2
 },
 "sources": {
  "twse": true,
  "tpex": true,
  "broker": false,
  "fundamentals": true,
  "overseas": true,
  "news": true,
  "history": true,
  "tdcc": true,
  "futures": false
 },
 "topic_momentum": {
  "記憶體": -16.36,
  "AI伺服器": -5.25,
  "晶圓代工": -9.54,
  "IC設計": -9.43,
  "CoWoS先進封裝": -4.6,
  "矽光子CPO": -16.82,
  "散熱": -7.69,
  "機器人": -2.03,
  "重電綠能": -1.27,
  "軍工航太": 7.44,
  "PCB": -14.33,
  "矽智財IP": -3.98,
  "被動元件": 3.17,
  "蘋果供應鏈": 12.17,
  "低軌衛星": 27.12,
  "航運": -0.89,
  "金融": 4.06,
  "網通": -4.29,
  "綠能": -9.68,
  "塑化": -5.46,
  "鋼鐵": -11.31,
  "生技新藥": 5.85
 },
 "topic_heat": {
  "記憶體": 7,
  "AI伺服器": 11,
  "晶圓代工": 1,
  "IC設計": 1,
  "CoWoS先進封裝": 2,
  "矽光子CPO": 3,
  "散熱": 4,
  "機器人": 27,
  "重電綠能": 3,
  "軍工航太": 8,
  "PCB": 14,
  "矽智財IP": 1,
  "被動元件": 3,
  "蘋果供應鏈": 0,
  "低軌衛星": 5,
  "航運": 2,
  "營建資產": 0,
  "金融": 0,
  "網通": 0,
  "綠能": 0,
  "塑化": 2,
  "鋼鐵": 0,
  "生技新藥": 3
 },
 "yahoo_ok": 306,
 "market_pulse": {
  "advancers": 1371,
  "decliners": 687,
  "unchanged": 181,
  "breadth_pct": 66.6,
  "inst_foreign": -777.8,
  "inst_trust": 76.0,
  "inst_dealer": -32.6,
  "inst_total": -734.4,
  "margin_chg_lots": 137315.0,
  "margin_up_count": 947,
  "hot_topics": [
   {
    "name": "機器人",
    "heat": 27,
    "mom": -2.0
   },
   {
    "name": "低軌衛星",
    "heat": 5,
    "mom": 27.1
   },
   {
    "name": "軍工航太",
    "heat": 8,
    "mom": 7.4
   }
  ],
  "mood": "neutral",
  "mood_text": "中性"
 }
}