{
 "status": "ok",
 "generated_at": "2026-07-07T20:16:14+08:00",
 "snapshot_days": 26,
 "date_range": [
  "20260529",
  "20260707"
 ],
 "recommendations_seen": 1040,
 "windows": [
  5,
  10,
  20,
  60
 ],
 "benchmark": "^TWII",
 "benchmark_ok": true,
 "groups": {
  "strong": {
   "5": {
    "avg": 0.41,
    "win_rate": 44.9,
    "alpha": 0.89,
    "n": 659
   },
   "10": {
    "avg": 1.79,
    "win_rate": 46.9,
    "alpha": 0.39,
    "n": 599
   },
   "20": {
    "avg": 0.92,
    "win_rate": 46.6,
    "alpha": -1.29,
    "n": 264
   },
   "60": {
    "avg": null,
    "win_rate": null,
    "alpha": null,
    "n": 0
   }
  },
  "mid": {
   "5": {
    "avg": 2.29,
    "win_rate": 59.1,
    "alpha": -1.13,
    "n": 181
   },
   "10": {
    "avg": 3.82,
    "win_rate": 45.7,
    "alpha": -0.73,
    "n": 81
   },
   "20": {
    "avg": 5.83,
    "win_rate": 43.8,
    "alpha": 1.29,
    "n": 16
   },
   "60": {
    "avg": null,
    "win_rate": null,
    "alpha": null,
    "n": 0
   }
  },
  "watch": {
   "5": {
    "avg": null,
    "win_rate": null,
    "alpha": null,
    "n": 0
   },
   "10": {
    "avg": null,
    "win_rate": null,
    "alpha": null,
    "n": 0
   },
   "20": {
    "avg": null,
    "win_rate": null,
    "alpha": null,
    "n": 0
   },
   "60": {
    "avg": null,
    "win_rate": null,
    "alpha": null,
    "n": 0
   }
  }
 },
 "by_market": {
  "twse": {
   "5": {
    "avg": 0.82,
    "win_rate": 47.6,
    "n": 771
   },
   "10": {
    "avg": 2.25,
    "win_rate": 46.8,
    "n": 618
   },
   "20": {
    "avg": 1.91,
    "win_rate": 49.2,
    "n": 236
   },
   "60": {
    "avg": null,
    "win_rate": null,
    "n": 0
   }
  },
  "tpex": {
   "5": {
    "avg": -2.55,
    "win_rate": 44.8,
    "n": 29
   },
   "10": {
    "avg": 0.58,
    "win_rate": 54.5,
    "n": 22
   },
   "20": {
    "avg": -13.33,
    "win_rate": 0.0,
    "n": 4
   },
   "60": {
    "avg": null,
    "win_rate": null,
    "n": 0
   }
  }
 },
 "factor_power": {
  "法人": {
   "5": 1.21,
   "10": 1.61,
   "20": 3.94,
   "60": null
  },
  "融資": {
   "5": -0.54,
   "10": -0.63,
   "20": 1.42,
   "60": null
  },
  "基本面": {
   "5": 1.11,
   "10": -0.67,
   "20": 4.63,
   "60": null
  },
  "國際": {
   "5": -0.37,
   "10": -2.43,
   "20": null,
   "60": null
  },
  "題材": {
   "5": null,
   "10": null,
   "20": null,
   "60": null
  },
  "技術": {
   "5": 0.4,
   "10": 0.53,
   "20": 3.85,
   "60": null
  }
 },
 "monotonic": {
  "5": null,
  "10": null,
  "20": null,
  "60": null
 },
 "note": "收益率=推薦日收盤後 N 交易日漲跌幅%;alpha=同期超越大盤幅度;面向預測力=該面向高分股 vs 低分股的 alpha 差。需累積足夠交易日樣本才有統計意義。"
}